fip_radiod/__init__.py
fip_radiod/fip_fetch.py
fip_radiod-0.2.3.dist-info/METADATA
fip_radiod-0.2.3.dist-info/WHEEL
fip_radiod-0.2.3.dist-info/entry_points.txt
fip_radiod-0.2.3.dist-info/top_level.txt
fip_radiod-0.2.3.dist-info/RECORD
