Metadata-Version: 2.2
Name: fip_radiod
Version: 0.2.3
Summary: Know what is currently playing on FIP
Project-URL: homepage, https://github.com/AdrienPlacais/fip_radiod
Requires-Python: >=3.10
Requires-Dist: requests<3,>=2.32.3
Requires-Dist: python-dotenv<2,>=1.0.1
Requires-Dist: requests<3,>=2.30.0
Requires-Dist: setuptools<73,>=72
Provides-Extra: test
Requires-Dist: pytest<9,>=8.3.2; extra == "test"
